ieeg/__init__.py
ieeg/io.py
ieeg/mt_filter.py
ieeg/navigate.py
ieeg/process.py
ieeg/arrays/__init__.py
ieeg/arrays/api.py
ieeg/arrays/label.py
ieeg/arrays/reshape.py
ieeg/calc/__init__.py
ieeg/calc/fast.py
ieeg/calc/oversample.py
ieeg/calc/scaling.py
ieeg/calc/stats.py
ieeg/calc/_fast/__init__.cpython-310-x86_64-linux-gnu.so
ieeg/calc/_fast/mixup.cpython-310-x86_64-linux-gnu.so
ieeg/calc/_fast/nanconcat.cpython-310-x86_64-linux-gnu.so
ieeg/calc/_fast/permgt.cpython-310-x86_64-linux-gnu.so
ieeg/calc/_fast/ufuncs.cpython-310-x86_64-linux-gnu.so
ieeg/decoding/__init__.py
ieeg/decoding/decode.py
ieeg/decoding/metrics.py
ieeg/decoding/models.py
ieeg/decoding/preprocessing_funcs.py
ieeg/decoding/joint_pca/__init__.py
ieeg/decoding/joint_pca/alignment_methods.py
ieeg/decoding/joint_pca/cross_pt_decoders.py
ieeg/decoding/joint_pca/utils.py
ieeg/timefreq/__init__.py
ieeg/timefreq/gamma.py
ieeg/timefreq/hilbert.cpython-310-x86_64-linux-gnu.so
ieeg/timefreq/multitaper.py
ieeg/timefreq/superlets.py
ieeg/timefreq/utils.py
ieeg/viz/__init__.py
ieeg/viz/ensemble.py
ieeg/viz/mri.py
ieeg/viz/parula.py
ieeg-0.7.0.dist-info/METADATA
ieeg-0.7.0.dist-info/WHEEL
ieeg-0.7.0.dist-info/top_level.txt
ieeg-0.7.0.dist-info/RECORD
ieeg-0.7.0.dist-info/licenses/LICENSE
