Metadata-Version: 2.4
Name: ieeg
Version: 0.7.0
Summary: A Python package for iEEG data processing.
Home-page: https://github.com/coganlab/IEEG_Pipelines
Author: Aaron Earle-Richardson
Author-email: Aaron Earle-Richardson <ae166@duke.edu>, Raymond Xiong <raymond.xiong@duke.edu>
License: MIT License
Project-URL: Homepage, https://github.com/coganlab/IEEG_Pipelines
Project-URL: Source, https://github.com/coganlab/IEEG_Pipelines
Project-URL: Issues, https://github.com/coganlab/IEEG_Pipelines/Issues
Project-URL: Documentation, https://ieeg-pipelines.readthedocs.io/en/latest/
Requires-Python: >=3.10
License-File: LICENSE
Requires-Dist: bids>=0.0
Requires-Dist: mne
Requires-Dist: mne-bids
Requires-Dist: numpy
Requires-Dist: matplotlib
Requires-Dist: scipy
Requires-Dist: scikit-learn
Requires-Dist: pandas
Requires-Dist: joblib>=1.3
Requires-Dist: psutil
Requires-Dist: pyvistaqt
Requires-Dist: pytz
Requires-Dist: pyqt5
Requires-Dist: tqdm
Requires-Dist: h5io
Requires-Dist: dipy
Requires-Dist: mne-qt-browser
Requires-Dist: edfio
Requires-Dist: array-api-compat
Requires-Dist: array-api-extra
Dynamic: author
Dynamic: home-page
Dynamic: license-file
